AUTHORS.rst
CONTRIBUTING.rst
HISTORY.rst
LICENSE
MANIFEST.in
README.rst
setup.cfg
setup.py
docs/Makefile
docs/authors.rst
docs/conf.py
docs/contributing.rst
docs/history.rst
docs/index.rst
docs/installation.rst
docs/make.bat
docs/readme.rst
docs/usage.rst
tc2calcu/__init__.py
tc2calcu/__main__.py
tc2calcu/cli.py
tc2calcu/tc2calcu.py
tc2calcu.egg-info/PKG-INFO
tc2calcu.egg-info/SOURCES.txt
tc2calcu.egg-info/dependency_links.txt
tc2calcu.egg-info/entry_points.txt
tc2calcu.egg-info/not-zip-safe
tc2calcu.egg-info/requires.txt
tc2calcu.egg-info/top_level.txt
tests/__init__.py
tests/test_tc2calcu.py